RPA/Moodle.py
RPA/__init__.py
rpa_moodle-2.0.0.dist-info/licenses/LICENSE
rpa_moodle-2.0.0.dist-info/METADATA
rpa_moodle-2.0.0.dist-info/WHEEL
rpa_moodle-2.0.0.dist-info/top_level.txt
rpa_moodle-2.0.0.dist-info/RECORD
