Metadata-Version: 2.4
Name: rpa-moodle
Version: 2.0.0
Summary: RPA library for Moodle automation with Robot Framework
Author-email: Khanh <khanh@example.com>
License-Expression: MIT
Project-URL: Homepage, https://github.com/khanh/rpa-moodle
Project-URL: Documentation, https://github.com/khanh/rpa-moodle#readme
Project-URL: Repository, https://github.com/khanh/rpa-moodle
Project-URL: Issues, https://github.com/khanh/rpa-moodle/issues
Keywords: robotframework,moodle,automation,rpa,testing,web-services,gemini-ai,auto-grading
Classifier: Development Status :: 4 - Beta
Classifier: Intended Audience :: Developers
Classifier: Operating System :: OS Independent
Classifier: Programming Language :: Python :: 3
Classifier: Programming Language :: Python :: 3.8
Classifier: Programming Language :: Python :: 3.9
Classifier: Programming Language :: Python :: 3.10
Classifier: Programming Language :: Python :: 3.11
Classifier: Programming Language :: Python :: 3.12
Classifier: Topic :: Software Development :: Testing
Classifier: Topic :: Software Development :: Libraries :: Python Modules
Classifier: Framework :: Robot Framework
Classifier: Framework :: Robot Framework :: Library
Requires-Python: >=3.8
License-File: LICENSE
Requires-Dist: requests>=2.31.0
Requires-Dist: pandas>=2.0.0
Requires-Dist: openpyxl>=3.1.0
Requires-Dist: robotframework>=6.0.0
Requires-Dist: google-auth>=2.0.0
Requires-Dist: google-auth-oauthlib>=1.0.0
Requires-Dist: google-api-python-client>=2.0.0
Requires-Dist: google-generativeai>=0.3.0
Requires-Dist: pillow>=10.0.0
Requires-Dist: importlib-metadata>=6.0.0
Provides-Extra: dev
Requires-Dist: pytest>=7.0.0; extra == "dev"
Requires-Dist: pytest-cov>=4.0.0; extra == "dev"
Requires-Dist: black>=23.0.0; extra == "dev"
Requires-Dist: flake8>=6.0.0; extra == "dev"
Dynamic: license-file
